pyrouge/__init__.py
pyrouge/base.py
pyrouge/rouge.py
pyrouge/tests/__init__.py
pyrouge/tests/test_build_summary.py
pyrouge/tests/test_rouge_compat.py
pyrouge/tools/ROUGE-1.5.5/README.txt
pyrouge/tools/ROUGE-1.5.5/RELEASE-NOTE.txt
pyrouge/tools/ROUGE-1.5.5/ROUGE-1.5.5.pl
pyrouge/tools/ROUGE-1.5.5/runROUGE-test.pl
pyrouge/tools/ROUGE-1.5.5/XML/DOM.pm
pyrouge/tools/ROUGE-1.5.5/XML/RegExp.pm
pyrouge/tools/ROUGE-1.5.5/XML/DOM/AttDef.pod
pyrouge/tools/ROUGE-1.5.5/XML/DOM/AttlistDecl.pod
pyrouge/tools/ROUGE-1.5.5/XML/DOM/Attr.pod
pyrouge/tools/ROUGE-1.5.5/XML/DOM/CDATASection.pod
pyrouge/tools/ROUGE-1.5.5/XML/DOM/CharacterData.pod
pyrouge/tools/ROUGE-1.5.5/XML/DOM/Comment.pod
pyrouge/tools/ROUGE-1.5.5/XML/DOM/DOMException.pm
pyrouge/tools/ROUGE-1.5.5/XML/DOM/DOMImplementation.pod
pyrouge/tools/ROUGE-1.5.5/XML/DOM/DocumentFragment.pod
pyrouge/tools/ROUGE-1.5.5/XML/DOM/DocumentType.pod
pyrouge/tools/ROUGE-1.5.5/XML/DOM/Element.pod
pyrouge/tools/ROUGE-1.5.5/XML/DOM/ElementDecl.pod
pyrouge/tools/ROUGE-1.5.5/XML/DOM/Entity.pod
pyrouge/tools/ROUGE-1.5.5/XML/DOM/EntityReference.pod
pyrouge/tools/ROUGE-1.5.5/XML/DOM/NamedNodeMap.pm
pyrouge/tools/ROUGE-1.5.5/XML/DOM/NamedNodeMap.pod
pyrouge/tools/ROUGE-1.5.5/XML/DOM/Node.pod
pyrouge/tools/ROUGE-1.5.5/XML/DOM/NodeList.pm
pyrouge/tools/ROUGE-1.5.5/XML/DOM/NodeList.pod
pyrouge/tools/ROUGE-1.5.5/XML/DOM/Notation.pod
pyrouge/tools/ROUGE-1.5.5/XML/DOM/Parser.pod
pyrouge/tools/ROUGE-1.5.5/XML/DOM/PerlSAX.pm
pyrouge/tools/ROUGE-1.5.5/XML/DOM/ProcessingInstruction.pod
pyrouge/tools/ROUGE-1.5.5/XML/DOM/Text.pod
pyrouge/tools/ROUGE-1.5.5/XML/DOM/XMLDecl.pod
pyrouge/tools/ROUGE-1.5.5/XML/Handler/BuildDOM.pm
pyrouge/tools/ROUGE-1.5.5/data/WordNet-2.0.exc.db
pyrouge/tools/ROUGE-1.5.5/data/smart_common_words.txt
pyrouge/tools/ROUGE-1.5.5/data/WordNet-1.6-Exceptions/adj.exc
pyrouge/tools/ROUGE-1.5.5/data/WordNet-1.6-Exceptions/adv.exc
pyrouge/tools/ROUGE-1.5.5/data/WordNet-1.6-Exceptions/buildExeptionDB.pl
tilse-0.2.1.dist-info/LICENSE
tilse-0.2.1.dist-info/METADATA
tilse-0.2.1.dist-info/WHEEL
tilse-0.2.1.dist-info/top_level.txt
tilse-0.2.1.dist-info/RECORD
