Metadata-Version: 2.1
Name: tilse
Version: 0.2.1
Summary: A toolkit for timeline summarization and evaluation.
Home-page: http://github.com/smartschat/tilse
Author: Sebastian Martschat
Author-email: sebastian.martschat@gmail.com
License: MIT
Keywords: NLP,CL,natural language processing,computational linguistics,summarization,text analytics
Platform: UNKNOWN
Classifier: Intended Audience :: Science/Research
Classifier: Topic :: Scientific/Engineering
Classifier: Topic :: Scientific/Engineering :: Artificial Intelligence
Classifier: Topic :: Text Processing
Requires-Dist: numpy
Requires-Dist: scipy
Requires-Dist: pathlib2
Requires-Dist: beautifulsoup4
Requires-Dist: scikit-learn
Requires-Dist: numba
Requires-Dist: spacy
Requires-Dist: textacy
Requires-Dist: nltk
